pokeme/__init__.py
pokeme/pokemon.csv
pokeme/random_pokemon.py
pokeme-1.0.1.dist-info/METADATA
pokeme-1.0.1.dist-info/WHEEL
pokeme-1.0.1.dist-info/top_level.txt
pokeme-1.0.1.dist-info/RECORD
