Metadata-Version: 2.1
Name: pokeme
Version: 1.0.1
Author: Farid Hernandez
Author-email: jaelfarid261@gmail.com
Requires-Dist: pandas
